{"name": "Seel", "evolution_id": null, "encounter_list": [{"version": "firered", "location": "seafoam-islands-b1f", "method": "walk", "min_level": 28, "max_level": 28, "rarity": 10}, {"version": "leafgreen", "location": "seafoam-islands-b1f", "method": "walk", "min_level": 28, "max_level": 28, "rarity": 10}, {"version": "firered", "location": "seafoam-islands-b2f", "method": "walk", "min_level": 30, "max_level": 30, "rarity": 10}, {"version": "firered", "location": "seafoam-islands-b2f", "method": "walk", "min_level": 32, "max_level": 32, "rarity": 10}, {"version": "leafgreen", "location": "seafoam-islands-b2f", "method": "walk", "min_level": 30, "max_level": 30, "rarity": 10}, {"version": "leafgreen", "location": "seafoam-islands-b2f", "method": "walk", "min_level": 32, "max_level": 32, "rarity": 10}, {"version": "firered", "location": "seafoam-islands-b3f", "method": "walk", "min_level": 30, "max_level": 30, "rarity": 20}, {"version": "firered", "location": "seafoam-islands-b3f", "method": "walk", "min_level": 32, "max_level": 32, "rarity": 20}, {"version": "firered", "location": "seafoam-islands-b3f", "method": "surf", "min_level": 25, "max_level": 35, "rarity": 60}, {"version": "leafgreen", "location": "seafoam-islands-b3f", "method": "walk", "min_level": 30, "max_level": 30, "rarity": 20}, {"version": "leafgreen", "location": "seafoam-islands-b3f", "method": "walk", "min_level": 32, "max_level": 32, "rarity": 20}, {"version": "leafgreen", "location": "seafoam-islands-b3f", "method": "surf", "min_level": 25, "max_level": 35, "rarity": 60}, {"version": "firered", "location": "seafoam-islands-b4f", "method": "walk", "min_level": 30, "max_level": 30, "rarity": 20}, {"version": "firered", "location": "seafoam-islands-b4f", "method": "walk", "min_level": 32, "max_level": 32, "rarity": 20}, {"version": "firered", "location": "seafoam-islands-b4f", "method": "walk", "min_level": 34, "max_level": 34, "rarity": 10}, {"version": "firered", "location": "seafoam-islands-b4f", "method": "surf", "min_level": 25, "max_level": 35, "rarity": 60}, {"version": "leafgreen", "location": "seafoam-islands-b4f", "method": "walk", "min_level": 30, "max_level": 30, "rarity": 20}, {"version": "leafgreen", "location": "seafoam-islands-b4f", "method": "walk", "min_level": 32, "max_level": 32, "rarity": 20}, {"version": "leafgreen", "location": "seafoam-islands-b4f", "method": "walk", "min_level": 34, "max_level": 34, "rarity": 10}, {"version": "leafgreen", "location": "seafoam-islands-b4f", "method": "surf", "min_level": 25, "max_level": 35, "rarity": 60}, {"version": "firered", "location": "icefall-cave-entrance", "method": "walk", "min_level": 43, "max_level": 43, "rarity": 20}, {"version": "firered", "location": "icefall-cave-entrance", "method": "walk", "min_level": 45, "max_level": 45, "rarity": 10}, {"version": "firered", "location": "icefall-cave-entrance", "method": "walk", "min_level": 47, "max_level": 47, "rarity": 10}, {"version": "firered", "location": "icefall-cave-entrance", "method": "surf", "min_level": 5, "max_level": 35, "rarity": 60}, {"version": "leafgreen", "location": "icefall-cave-entrance", "method": "walk", "min_level": 43, "max_level": 43, "rarity": 20}, {"version": "leafgreen", "location": "icefall-cave-entrance", "method": "walk", "min_level": 45, "max_level": 45, "rarity": 10}, {"version": "leafgreen", "location": "icefall-cave-entrance", "method": "walk", "min_level": 47, "max_level": 47, "rarity": 10}, {"version": "leafgreen", "location": "icefall-cave-entrance", "method": "surf", "min_level": 5, "max_level": 35, "rarity": 60}, {"version": "firered", "location": "icefall-cave-1f", "method": "walk", "min_level": 45, "max_level": 45, "rarity": 10}, {"version": "leafgreen", "location": "icefall-cave-1f", "method": "walk", "min_level": 45, "max_level": 45, "rarity": 10}, {"version": "firered", "location": "icefall-cave-b1f", "method": "walk", "min_level": 45, "max_level": 45, "rarity": 10}, {"version": "leafgreen", "location": "icefall-cave-b1f", "method": "walk", "min_level": 45, "max_level": 45, "rarity": 10}, {"version": "firered", "location": "icefall-cave-waterfall", "method": "walk", "min_level": 43, "max_level": 43, "rarity": 20}, {"version": "firered", "location": "icefall-cave-waterfall", "method": "walk", "min_level": 45, "max_level": 45, "rarity": 10}, {"version": "firered", "location": "icefall-cave-waterfall", "method": "walk", "min_level": 47, "max_level": 47, "rarity": 10}, {"version": "leafgreen", "location": "icefall-cave-waterfall", "method": "walk", "min_level": 43, "max_level": 43, "rarity": 20}, {"version": "leafgreen", "location": "icefall-cave-waterfall", "method": "walk", "min_level": 45, "max_level": 45, "rarity": 10}, {"version": "leafgreen", "location": "icefall-cave-waterfall", "method": "walk", "min_level": 47, "max_level": 47, "rarity": 10}]}